{"Stock Name": "AMAT", "link": "https://finance.yahoo.com/quote/AMAT/key-statistics/", "Company Name": "Applied Materials, Inc. ", "Stock Value": "173.20", "Market Cap": "143.90B ", "Enterprise Value": "140.69B ", "Trailing P/E": "20.27 ", "Forward P/E": "17.99 ", "Enterprise Value/EBITDA": "16.00 ", "Profit Margin": "27.74%", "Operating Margin": "28.65%", "Quarterly Revenue Growth": "5.50%", "Quarterly Earnings Growth": "9.30%", "Beta (5Y Monthly)": "1.55", "Percentage by insiders": "0.30%", "Forward Annual Dividend Rate": "1.6", "5 Year Average Dividend Yield": "0.93"}